userlex/__about__.py
userlex/__init__.py
userlex/cli/__init__.py
userlex/social_media/__init__.py
userlex/social_media/base.py
userlex/social_media/facebook.py
userlex/social_media/instagram.py
userlex/social_media/line.py
userlex/social_media/skype.py
userlex/social_media/telegram.py
userlex-0.0.2.dist-info/METADATA
userlex-0.0.2.dist-info/WHEEL
userlex-0.0.2.dist-info/entry_points.txt
userlex-0.0.2.dist-info/top_level.txt
userlex-0.0.2.dist-info/RECORD
