Metadata-Version: 2.1
Name: userlex
Version: 0.0.2
Summary: A library to extract social media and other useful things
Home-page: https://github.com/dvershinin/userlex
Author: Danila Vershinin
Author-email: info@getpagespeed.com
License: BSD
Classifier: Intended Audience :: Developers
Provides-Extra: tests
Requires-Dist: pytest ; extra == 'tests'
Requires-Dist: flake8 ; extra == 'tests'
Requires-Dist: pyyaml ; extra == 'tests'
